[
  {
    "img": "https://source.unsplash.com/featured/?linux,computer",
    "url": "/scenarios/0",
    "title": "Systèmes libres sur ordinateurs, tablettes et smartphones",
    "content": "L’objectif de ce scénario est de réduire la dépendance aux systèmes propriétaires comme Windows, Android ou iOS afin de lutter contre l’obsolescence logicielle..."
  },
  {
    "img": "https://source.unsplash.com/featured/?office,documents",
    "url": "/scenarios/1",
    "title": "Bureautique libre pour élèves, étudiants et enseignants",
    "content": "Les outils bureautiques libres permettent d’accéder gratuitement..."
  },
  {
    "img": "https://source.unsplash.com/featured/?refurbished,laptop",
    "url": "/scenarios/2",
    "title": "Reconditionnement pour l’équipement des élèves",
    "content": "Le reconditionnement permet aux élèves, étudiants et familles..."
  },
  {
    "img": "https://source.unsplash.com/featured/?privacy,data",
    "url": "/scenarios/3",
    "title": "Souveraineté des données des élèves et des familles",
    "content": "Ce scénario vise à garantir que les données personnelles..."
  },
  {
    "img": "https://source.unsplash.com/featured/?smartphone,communication",
    "url": "/scenarios/4",
    "title": "Messageries et communications scolaires sur mobiles",
    "content": "Les échanges scolaires se font aujourd’hui majoritairement via..."
  },
  {
    "img": "https://source.unsplash.com/featured/?video,education",
    "url": "/scenarios/5",
    "title": "Plateformes vidéo éducatives libres pour tous",
    "content": "La vidéo est devenue un outil central pour l’apprentissage..."
  },
  {
    "img": "https://source.unsplash.com/featured/?accessibility,education",
    "url": "/scenarios/6",
    "title": "Accessibilité numérique sur tous les supports",
    "content": "Assurer l’accessibilité des outils numériques permet à tous..."
  },
  {
    "img": "https://source.unsplash.com/featured/?ecology,technology",
    "url": "/scenarios/7",
    "title": "Sobriété numérique des usages élèves et étudiants",
    "content": "La sobriété numérique encourage des pratiques plus respectueuses..."
  },
  {
    "img": "https://source.unsplash.com/featured/?smartphone,apps",
    "url": "/scenarios/8",
    "title": "Dépendance aux stores d’applications sur smartphones",
    "content": "Ce scénario met en lumière la dépendance aux stores dominants..."
  },
  {
    "img": "https://source.unsplash.com/featured/?school,platform",
    "url": "/scenarios/9",
    "title": "Plateformes de travail et de gestion scolaires libres",
    "content": "Les plateformes de gestion scolaire privées collectent..."
  },
  {
    "img": "https://source.unsplash.com/featured/?maps,navigation",
    "url": "/scenarios/10",
    "title": "Cartographie, recherche et usages numériques alternatifs",
    "content": "La recherche d'information et la cartographie sont aujourd’hui..."
  },
  {
    "img": "https://source.unsplash.com/featured/?education,training",
    "url": "/scenarios/11",
    "title": "Formation massive au numérique libre",
    "content": "Le numérique libre constitue un socle essentiel..."
  },
  {
    "img": "https://source.unsplash.com/featured/?student,privacy",
    "url": "/scenarios/12",
    "title": "Protéger sa vie privée en tant qu’étudiant",
    "content": "Les étudiants utilisent quotidiennement des applications..."
  },
  {
    "img": "https://source.unsplash.com/featured/?student,laptop",
    "url": "/scenarios/13",
    "title": "Étudier sans payer d’abonnements",
    "content": "Les étudiants sont souvent confrontés à des logiciels..."
  },
  {
    "img": "https://source.unsplash.com/featured/?opensource,customization",
    "url": "/scenarios/14",
    "title": "Garder le contrôle sur ses outils",
    "content": "Le contrôle de ses outils numériques est essentiel..."
  },
  {
    "img": "https://source.unsplash.com/featured/?oldcomputer,linux",
    "url": "/scenarios/15",
    "title": "Faire durer son ordinateur plus longtemps",
    "content": "L’obsolescence logicielle oblige souvent à remplacer..."
  },
  {
    "img": "https://source.unsplash.com/featured/?skills,career",
    "url": "/scenarios/16",
    "title": "Développer des compétences utiles pour les études et l’emploi",
    "content": "Apprendre à utiliser des logiciels libres, comprendre..."
  },
  {
    "img": "https://source.unsplash.com/featured/?pme,budget",
    "url": "/scenarios/17",
    "title": "Réduction des coûts logiciels dans une PME",
    "content": "Les PME font face à une augmentation constante des coûts..."
  },
  {
    "img": "https://source.unsplash.com/featured/?security,data",
    "url": "/scenarios/18",
    "title": "Protection des données et conformité réglementaire",
    "content": "Les PME manipulent des données sensibles..."
  },
  {
    "img": "https://source.unsplash.com/featured/?technology,freedom",
    "url": "/scenarios/19",
    "title": "Indépendance technologique de la PME",
    "content": "L’indépendance technologique permet à une PME..."
  },
  {
    "img": "https://source.unsplash.com/featured/?hardware,lifecycle",
    "url": "/scenarios/20",
    "title": "Allongement de la durée de vie du matériel",
    "content": "Le renouvellement informatique représente une grande dépense..."
  }
]